Classfile jar:file:///C:/Users/henry/.m2/repository/com/hypixel/hytale/hytale-server/2026.01.15/hytale-server-2026.01.15.jar!/com/hypixel/hytale/server/core/asset/AssetPackRegisterEvent.class
  Last modified Jan 17, 2026; size 762 bytes
  SHA-256 checksum 7c1af9b89d2c86bea513307cbcd83130603fc9eb828c55a2ccc7ff9ca54eb5cd
  Compiled from "AssetPackRegisterEvent.java"
public class com.hypixel.hytale.server.core.asset.AssetPackRegisterEvent extends java.lang.Object implements com.hypixel.hytale.event.IEvent<java.lang.Void>
  minor version: 0
  major version: 65
  flags: (0x0021) ACC_PUBLIC, ACC_SUPER
  this_class: #8                          // com/hypixel/hytale/server/core/asset/AssetPackRegisterEvent
  super_class: #2                         // java/lang/Object
  interfaces: 1, fields: 1, methods: 2, attributes: 2
Constant pool:
   #1 = Methodref          #2.#3          // java/lang/Object."<init>":()V
   #2 = Class              #4             // java/lang/Object
   #3 = NameAndType        #5:#6          // "<init>":()V
   #4 = Utf8               java/lang/Object
   #5 = Utf8               <init>
   #6 = Utf8               ()V
   #7 = Fieldref           #8.#9          // com/hypixel/hytale/server/core/asset/AssetPackRegisterEvent.assetPack:Lcom/hypixel/hytale/assetstore/AssetPack;
   #8 = Class              #10            // com/hypixel/hytale/server/core/asset/AssetPackRegisterEvent
   #9 = NameAndType        #11:#12        // assetPack:Lcom/hypixel/hytale/assetstore/AssetPack;
  #10 = Utf8               com/hypixel/hytale/server/core/asset/AssetPackRegisterEvent
  #11 = Utf8               assetPack
  #12 = Utf8               Lcom/hypixel/hytale/assetstore/AssetPack;
  #13 = Class              #14            // com/hypixel/hytale/event/IEvent
  #14 = Utf8               com/hypixel/hytale/event/IEvent
  #15 = Utf8               (Lcom/hypixel/hytale/assetstore/AssetPack;)V
  #16 = Utf8               Code
  #17 = Utf8               LineNumberTable
  #18 = Utf8               LocalVariableTable
  #19 = Utf8               this
  #20 = Utf8               Lcom/hypixel/hytale/server/core/asset/AssetPackRegisterEvent;
  #21 = Utf8               getAssetPack
  #22 = Utf8               ()Lcom/hypixel/hytale/assetstore/AssetPack;
  #23 = Utf8               Signature
  #24 = Utf8               Ljava/lang/Object;Lcom/hypixel/hytale/event/IEvent<Ljava/lang/Void;>;
  #25 = Utf8               SourceFile
  #26 = Utf8               AssetPackRegisterEvent.java
{
  private final com.hypixel.hytale.assetstore.AssetPack assetPack;
    descriptor: Lcom/hypixel/hytale/assetstore/AssetPack;
    flags: (0x0012) ACC_PRIVATE, ACC_FINAL

  public com.hypixel.hytale.server.core.asset.AssetPackRegisterEvent(com.hypixel.hytale.assetstore.AssetPack);
    descriptor: (Lcom/hypixel/hytale/assetstore/AssetPack;)V
    flags: (0x0001) ACC_PUBLIC
    Code:
      stack=2, locals=2, args_size=2
         0: aload_0
         1: invokespecial #1                  // Method java/lang/Object."<init>":()V
         4: aload_0
         5: aload_1
         6: putfield      #7                  // Field assetPack:Lcom/hypixel/hytale/assetstore/AssetPack;
         9: return
      LineNumberTable:
        line 10: 0
        line 11: 4
        line 12: 9
      LocalVariableTable:
        Start  Length  Slot  Name   Signature
            0      10     0  this   Lcom/hypixel/hytale/server/core/asset/AssetPackRegisterEvent;
            0      10     1 assetPack   Lcom/hypixel/hytale/assetstore/AssetPack;

  public com.hypixel.hytale.assetstore.AssetPack getAssetPack();
    descriptor: ()Lcom/hypixel/hytale/assetstore/AssetPack;
    flags: (0x0001) ACC_PUBLIC
    Code:
      stack=1, locals=1, args_size=1
         0: aload_0
         1: getfield      #7                  // Field assetPack:Lcom/hypixel/hytale/assetstore/AssetPack;
         4: areturn
      LineNumberTable:
        line 15: 0
      LocalVariableTable:
        Start  Length  Slot  Name   Signature
            0       5     0  this   Lcom/hypixel/hytale/server/core/asset/AssetPackRegisterEvent;
}
Signature: #24                          // Ljava/lang/Object;Lcom/hypixel/hytale/event/IEvent<Ljava/lang/Void;>;
SourceFile: "AssetPackRegisterEvent.java"
