Classfile jar:file:///C:/Users/henry/.m2/repository/com/hypixel/hytale/hytale-server/2026.01.15/hytale-server-2026.01.15.jar!/com/hypixel/hytale/server/core/asset/common/BlockyAnimationCache.class
  Last modified Jan 17, 2026; size 6148 bytes
  SHA-256 checksum dfb48d3601b81019560821233f9b2657e3ccb3fa5e0eedc99129bd9cc5f0717e
  Compiled from "BlockyAnimationCache.java"
public class com.hypixel.hytale.server.core.asset.common.BlockyAnimationCache
  minor version: 0
  major version: 65
  flags: (0x0021) ACC_PUBLIC, ACC_SUPER
  this_class: #8                          // com/hypixel/hytale/server/core/asset/common/BlockyAnimationCache
  super_class: #2                         // java/lang/Object
  interfaces: 0, fields: 2, methods: 9, attributes: 4
Constant pool:
    #1 = Methodref          #2.#3         // java/lang/Object."<init>":()V
    #2 = Class              #4            // java/lang/Object
    #3 = NameAndType        #5:#6         // "<init>":()V
    #4 = Utf8               java/lang/Object
    #5 = Utf8               <init>
    #6 = Utf8               ()V
    #7 = Fieldref           #8.#9         // com/hypixel/hytale/server/core/asset/common/BlockyAnimationCache.animations:Ljava/util/Map;
    #8 = Class              #10           // com/hypixel/hytale/server/core/asset/common/BlockyAnimationCache
    #9 = NameAndType        #11:#12       // animations:Ljava/util/Map;
   #10 = Utf8               com/hypixel/hytale/server/core/asset/common/BlockyAnimationCache
   #11 = Utf8               animations
   #12 = Utf8               Ljava/util/Map;
   #13 = InterfaceMethodref #14.#15       // java/util/Map.get:(Ljava/lang/Object;)Ljava/lang/Object;
   #14 = Class              #16           // java/util/Map
   #15 = NameAndType        #17:#18       // get:(Ljava/lang/Object;)Ljava/lang/Object;
   #16 = Utf8               java/util/Map
   #17 = Utf8               get
   #18 = Utf8               (Ljava/lang/Object;)Ljava/lang/Object;
   #19 = Class              #20           // com/hypixel/hytale/server/core/asset/common/BlockyAnimationCache$BlockyAnimation
   #20 = Utf8               com/hypixel/hytale/server/core/asset/common/BlockyAnimationCache$BlockyAnimation
   #21 = Methodref          #22.#23       // java/util/concurrent/CompletableFuture.completedFuture:(Ljava/lang/Object;)Ljava/util/concurrent/CompletableFuture;
   #22 = Class              #24           // java/util/concurrent/CompletableFuture
   #23 = NameAndType        #25:#26       // completedFuture:(Ljava/lang/Object;)Ljava/util/concurrent/CompletableFuture;
   #24 = Utf8               java/util/concurrent/CompletableFuture
   #25 = Utf8               completedFuture
   #26 = Utf8               (Ljava/lang/Object;)Ljava/util/concurrent/CompletableFuture;
   #27 = Methodref          #28.#29       // com/hypixel/hytale/server/core/asset/common/CommonAssetRegistry.getByName:(Ljava/lang/String;)Lcom/hypixel/hytale/server/core/asset/common/CommonAsset;
   #28 = Class              #30           // com/hypixel/hytale/server/core/asset/common/CommonAssetRegistry
   #29 = NameAndType        #31:#32       // getByName:(Ljava/lang/String;)Lcom/hypixel/hytale/server/core/asset/common/CommonAsset;
   #30 = Utf8               com/hypixel/hytale/server/core/asset/common/CommonAssetRegistry
   #31 = Utf8               getByName
   #32 = Utf8               (Ljava/lang/String;)Lcom/hypixel/hytale/server/core/asset/common/CommonAsset;
   #33 = Methodref          #8.#34        // com/hypixel/hytale/server/core/asset/common/BlockyAnimationCache.get0:(Lcom/hypixel/hytale/server/core/asset/common/CommonAsset;)Ljava/util/concurrent/CompletableFuture;
   #34 = NameAndType        #35:#36       // get0:(Lcom/hypixel/hytale/server/core/asset/common/CommonAsset;)Ljava/util/concurrent/CompletableFuture;
   #35 = Utf8               get0
   #36 = Utf8               (Lcom/hypixel/hytale/server/core/asset/common/CommonAsset;)Ljava/util/concurrent/CompletableFuture;
   #37 = Methodref          #38.#39       // com/hypixel/hytale/server/core/asset/common/CommonAsset.getName:()Ljava/lang/String;
   #38 = Class              #40           // com/hypixel/hytale/server/core/asset/common/CommonAsset
   #39 = NameAndType        #41:#42       // getName:()Ljava/lang/String;
   #40 = Utf8               com/hypixel/hytale/server/core/asset/common/CommonAsset
   #41 = Utf8               getName
   #42 = Utf8               ()Ljava/lang/String;
   #43 = Methodref          #22.#44       // java/util/concurrent/CompletableFuture.join:()Ljava/lang/Object;
   #44 = NameAndType        #45:#46       // join:()Ljava/lang/Object;
   #45 = Utf8               join
   #46 = Utf8               ()Ljava/lang/Object;
   #47 = Methodref          #38.#48       // com/hypixel/hytale/server/core/asset/common/CommonAsset.getBlob:()Ljava/util/concurrent/CompletableFuture;
   #48 = NameAndType        #49:#50       // getBlob:()Ljava/util/concurrent/CompletableFuture;
   #49 = Utf8               getBlob
   #50 = Utf8               ()Ljava/util/concurrent/CompletableFuture;
   #51 = InvokeDynamic      #0:#52        // #0:apply:(Ljava/lang/String;)Ljava/util/function/Function;
   #52 = NameAndType        #53:#54       // apply:(Ljava/lang/String;)Ljava/util/function/Function;
   #53 = Utf8               apply
   #54 = Utf8               (Ljava/lang/String;)Ljava/util/function/Function;
   #55 = Methodref          #22.#56       // java/util/concurrent/CompletableFuture.thenApply:(Ljava/util/function/Function;)Ljava/util/concurrent/CompletableFuture;
   #56 = NameAndType        #57:#58       // thenApply:(Ljava/util/function/Function;)Ljava/util/concurrent/CompletableFuture;
   #57 = Utf8               thenApply
   #58 = Utf8               (Ljava/util/function/Function;)Ljava/util/concurrent/CompletableFuture;
   #59 = Methodref          #60.#61       // com/hypixel/hytale/common/util/CompletableFutureUtil._catch:(Ljava/util/concurrent/CompletableFuture;)Ljava/util/concurrent/CompletableFuture;
   #60 = Class              #62           // com/hypixel/hytale/common/util/CompletableFutureUtil
   #61 = NameAndType        #63:#64       // _catch:(Ljava/util/concurrent/CompletableFuture;)Ljava/util/concurrent/CompletableFuture;
   #62 = Utf8               com/hypixel/hytale/common/util/CompletableFutureUtil
   #63 = Utf8               _catch
   #64 = Utf8               (Ljava/util/concurrent/CompletableFuture;)Ljava/util/concurrent/CompletableFuture;
   #65 = InterfaceMethodref #14.#66       // java/util/Map.remove:(Ljava/lang/Object;)Ljava/lang/Object;
   #66 = NameAndType        #67:#18       // remove:(Ljava/lang/Object;)Ljava/lang/Object;
   #67 = Utf8               remove
   #68 = Class              #69           // java/lang/String
   #69 = Utf8               java/lang/String
   #70 = Fieldref           #71.#72       // java/nio/charset/StandardCharsets.UTF_8:Ljava/nio/charset/Charset;
   #71 = Class              #73           // java/nio/charset/StandardCharsets
   #72 = NameAndType        #74:#75       // UTF_8:Ljava/nio/charset/Charset;
   #73 = Utf8               java/nio/charset/StandardCharsets
   #74 = Utf8               UTF_8
   #75 = Utf8               Ljava/nio/charset/Charset;
   #76 = Methodref          #68.#77       // java/lang/String."<init>":([BLjava/nio/charset/Charset;)V
   #77 = NameAndType        #5:#78        // "<init>":([BLjava/nio/charset/Charset;)V
   #78 = Utf8               ([BLjava/nio/charset/Charset;)V
   #79 = Methodref          #80.#81       // com/hypixel/hytale/codec/util/RawJsonReader.fromJsonString:(Ljava/lang/String;)Lcom/hypixel/hytale/codec/util/RawJsonReader;
   #80 = Class              #82           // com/hypixel/hytale/codec/util/RawJsonReader
   #81 = NameAndType        #83:#84       // fromJsonString:(Ljava/lang/String;)Lcom/hypixel/hytale/codec/util/RawJsonReader;
   #82 = Utf8               com/hypixel/hytale/codec/util/RawJsonReader
   #83 = Utf8               fromJsonString
   #84 = Utf8               (Ljava/lang/String;)Lcom/hypixel/hytale/codec/util/RawJsonReader;
   #85 = Fieldref           #86.#87       // com/hypixel/hytale/codec/ExtraInfo.THREAD_LOCAL:Ljava/lang/ThreadLocal;
   #86 = Class              #88           // com/hypixel/hytale/codec/ExtraInfo
   #87 = NameAndType        #89:#90       // THREAD_LOCAL:Ljava/lang/ThreadLocal;
   #88 = Utf8               com/hypixel/hytale/codec/ExtraInfo
   #89 = Utf8               THREAD_LOCAL
   #90 = Utf8               Ljava/lang/ThreadLocal;
   #91 = Methodref          #92.#93       // java/lang/ThreadLocal.get:()Ljava/lang/Object;
   #92 = Class              #94           // java/lang/ThreadLocal
   #93 = NameAndType        #17:#46       // get:()Ljava/lang/Object;
   #94 = Utf8               java/lang/ThreadLocal
   #95 = Fieldref           #19.#96       // com/hypixel/hytale/server/core/asset/common/BlockyAnimationCache$BlockyAnimation.CODEC:Lcom/hypixel/hytale/codec/builder/BuilderCodec;
   #96 = NameAndType        #97:#98       // CODEC:Lcom/hypixel/hytale/codec/builder/BuilderCodec;
   #97 = Utf8               CODEC
   #98 = Utf8               Lcom/hypixel/hytale/codec/builder/BuilderCodec;
   #99 = Methodref          #100.#101     // com/hypixel/hytale/codec/builder/BuilderCodec.decodeJson:(Lcom/hypixel/hytale/codec/util/RawJsonReader;Lcom/hypixel/hytale/codec/ExtraInfo;)Ljava/lang/Object;
  #100 = Class              #102          // com/hypixel/hytale/codec/builder/BuilderCodec
  #101 = NameAndType        #103:#104     // decodeJson:(Lcom/hypixel/hytale/codec/util/RawJsonReader;Lcom/hypixel/hytale/codec/ExtraInfo;)Ljava/lang/Object;
  #102 = Utf8               com/hypixel/hytale/codec/builder/BuilderCodec
  #103 = Utf8               decodeJson
  #104 = Utf8               (Lcom/hypixel/hytale/codec/util/RawJsonReader;Lcom/hypixel/hytale/codec/ExtraInfo;)Ljava/lang/Object;
  #105 = Methodref          #86.#106      // com/hypixel/hytale/codec/ExtraInfo.getValidationResults:()Lcom/hypixel/hytale/codec/validation/ValidationResults;
  #106 = NameAndType        #107:#108     // getValidationResults:()Lcom/hypixel/hytale/codec/validation/ValidationResults;
  #107 = Utf8               getValidationResults
  #108 = Utf8               ()Lcom/hypixel/hytale/codec/validation/ValidationResults;
  #109 = Fieldref           #8.#110       // com/hypixel/hytale/server/core/asset/common/BlockyAnimationCache.LOGGER:Lcom/hypixel/hytale/logger/HytaleLogger;
  #110 = NameAndType        #111:#112     // LOGGER:Lcom/hypixel/hytale/logger/HytaleLogger;
  #111 = Utf8               LOGGER
  #112 = Utf8               Lcom/hypixel/hytale/logger/HytaleLogger;
  #113 = Methodref          #114.#115     // com/hypixel/hytale/codec/validation/ValidationResults.logOrThrowValidatorExceptions:(Lcom/hypixel/hytale/logger/HytaleLogger;)V
  #114 = Class              #116          // com/hypixel/hytale/codec/validation/ValidationResults
  #115 = NameAndType        #117:#118     // logOrThrowValidatorExceptions:(Lcom/hypixel/hytale/logger/HytaleLogger;)V
  #116 = Utf8               com/hypixel/hytale/codec/validation/ValidationResults
  #117 = Utf8               logOrThrowValidatorExceptions
  #118 = Utf8               (Lcom/hypixel/hytale/logger/HytaleLogger;)V
  #119 = InterfaceMethodref #14.#120      // java/util/Map.put:(Ljava/lang/Object;Ljava/lang/Object;)Ljava/lang/Object;
  #120 = NameAndType        #121:#122     // put:(Ljava/lang/Object;Ljava/lang/Object;)Ljava/lang/Object;
  #121 = Utf8               put
  #122 = Utf8               (Ljava/lang/Object;Ljava/lang/Object;)Ljava/lang/Object;
  #123 = Class              #124          // java/io/IOException
  #124 = Utf8               java/io/IOException
  #125 = Methodref          #126.#127     // com/hypixel/hytale/sneakythrow/SneakyThrow.sneakyThrow:(Ljava/lang/Throwable;)Ljava/lang/RuntimeException;
  #126 = Class              #128          // com/hypixel/hytale/sneakythrow/SneakyThrow
  #127 = NameAndType        #129:#130     // sneakyThrow:(Ljava/lang/Throwable;)Ljava/lang/RuntimeException;
  #128 = Utf8               com/hypixel/hytale/sneakythrow/SneakyThrow
  #129 = Utf8               sneakyThrow
  #130 = Utf8               (Ljava/lang/Throwable;)Ljava/lang/RuntimeException;
  #131 = Methodref          #132.#133     // com/hypixel/hytale/logger/HytaleLogger.forEnclosingClass:()Lcom/hypixel/hytale/logger/HytaleLogger;
  #132 = Class              #134          // com/hypixel/hytale/logger/HytaleLogger
  #133 = NameAndType        #135:#136     // forEnclosingClass:()Lcom/hypixel/hytale/logger/HytaleLogger;
  #134 = Utf8               com/hypixel/hytale/logger/HytaleLogger
  #135 = Utf8               forEnclosingClass
  #136 = Utf8               ()Lcom/hypixel/hytale/logger/HytaleLogger;
  #137 = Class              #138          // java/util/concurrent/ConcurrentHashMap
  #138 = Utf8               java/util/concurrent/ConcurrentHashMap
  #139 = Methodref          #137.#3       // java/util/concurrent/ConcurrentHashMap."<init>":()V
  #140 = Utf8               Signature
  #141 = Utf8               Ljava/util/Map<Ljava/lang/String;Lcom/hypixel/hytale/server/core/asset/common/BlockyAnimationCache$BlockyAnimation;>;
  #142 = Utf8               Code
  #143 = Utf8               LineNumberTable
  #144 = Utf8               LocalVariableTable
  #145 = Utf8               this
  #146 = Utf8               Lcom/hypixel/hytale/server/core/asset/common/BlockyAnimationCache;
  #147 = Utf8               (Ljava/lang/String;)Ljava/util/concurrent/CompletableFuture;
  #148 = Utf8               name
  #149 = Utf8               Ljava/lang/String;
  #150 = Utf8               animationData
  #151 = Utf8               Lcom/hypixel/hytale/server/core/asset/common/BlockyAnimationCache$BlockyAnimation;
  #152 = Utf8               asset
  #153 = Utf8               Lcom/hypixel/hytale/server/core/asset/common/CommonAsset;
  #154 = Utf8               StackMapTable
  #155 = Utf8               (Ljava/lang/String;)Ljava/util/concurrent/CompletableFuture<Lcom/hypixel/hytale/server/core/asset/common/BlockyAnimationCache$BlockyAnimation;>;
  #156 = Utf8               RuntimeVisibleAnnotations
  #157 = Utf8               Ljavax/annotation/Nonnull;
  #158 = Utf8               (Lcom/hypixel/hytale/server/core/asset/common/CommonAsset;)Ljava/util/concurrent/CompletableFuture<Lcom/hypixel/hytale/server/core/asset/common/BlockyAnimationCache$BlockyAnimation;>;
  #159 = Utf8               RuntimeVisibleParameterAnnotations
  #160 = Utf8               getNow
  #161 = Utf8               (Ljava/lang/String;)Lcom/hypixel/hytale/server/core/asset/common/BlockyAnimationCache$BlockyAnimation;
  #162 = Utf8               Ljavax/annotation/Nullable;
  #163 = Utf8               (Lcom/hypixel/hytale/server/core/asset/common/CommonAsset;)Lcom/hypixel/hytale/server/core/asset/common/BlockyAnimationCache$BlockyAnimation;
  #164 = Utf8               invalidate
  #165 = Utf8               (Ljava/lang/String;)V
  #166 = Utf8               lambda$get0$0
  #167 = Utf8               (Ljava/lang/String;[B)Lcom/hypixel/hytale/server/core/asset/common/BlockyAnimationCache$BlockyAnimation;
  #168 = Utf8               extraInfo
  #169 = Utf8               Lcom/hypixel/hytale/codec/ExtraInfo;
  #170 = Utf8               newAnimationData
  #171 = Utf8               e
  #172 = Utf8               Ljava/io/IOException;
  #173 = Utf8               bytes
  #174 = Utf8               [B
  #175 = Utf8               str
  #176 = Utf8               reader
  #177 = Utf8               Lcom/hypixel/hytale/codec/util/RawJsonReader;
  #178 = Class              #174          // "[B"
  #179 = Utf8               <clinit>
  #180 = Utf8               SourceFile
  #181 = Utf8               BlockyAnimationCache.java
  #182 = Utf8               NestMembers
  #183 = Utf8               BootstrapMethods
  #184 = MethodType         #18           //  (Ljava/lang/Object;)Ljava/lang/Object;
  #185 = MethodHandle       6:#186        // REF_invokeStatic com/hypixel/hytale/server/core/asset/common/BlockyAnimationCache.lambda$get0$0:(Ljava/lang/String;[B)Lcom/hypixel/hytale/server/core/asset/common/BlockyAnimationCache$BlockyAnimation;
  #186 = Methodref          #8.#187       // com/hypixel/hytale/server/core/asset/common/BlockyAnimationCache.lambda$get0$0:(Ljava/lang/String;[B)Lcom/hypixel/hytale/server/core/asset/common/BlockyAnimationCache$BlockyAnimation;
  #187 = NameAndType        #166:#167     // lambda$get0$0:(Ljava/lang/String;[B)Lcom/hypixel/hytale/server/core/asset/common/BlockyAnimationCache$BlockyAnimation;
  #188 = MethodType         #189          //  ([B)Lcom/hypixel/hytale/server/core/asset/common/BlockyAnimationCache$BlockyAnimation;
  #189 = Utf8               ([B)Lcom/hypixel/hytale/server/core/asset/common/BlockyAnimationCache$BlockyAnimation;
  #190 = MethodHandle       6:#191        // REF_invokeStatic java/lang/invoke/LambdaMetafactory.metafactory:(Ljava/lang/invoke/MethodHandles$Lookup;Ljava/lang/String;Ljava/lang/invoke/MethodType;Ljava/lang/invoke/MethodType;Ljava/lang/invoke/MethodHandle;Ljava/lang/invoke/MethodType;)Ljava/lang/invoke/CallSite;
  #191 = Methodref          #192.#193     // java/lang/invoke/LambdaMetafactory.metafactory:(Ljava/lang/invoke/MethodHandles$Lookup;Ljava/lang/String;Ljava/lang/invoke/MethodType;Ljava/lang/invoke/MethodType;Ljava/lang/invoke/MethodHandle;Ljava/lang/invoke/MethodType;)Ljava/lang/invoke/CallSite;
  #192 = Class              #194          // java/lang/invoke/LambdaMetafactory
  #193 = NameAndType        #195:#196     // metafactory:(Ljava/lang/invoke/MethodHandles$Lookup;Ljava/lang/String;Ljava/lang/invoke/MethodType;Ljava/lang/invoke/MethodType;Ljava/lang/invoke/MethodHandle;Ljava/lang/invoke/MethodType;)Ljava/lang/invoke/CallSite;
  #194 = Utf8               java/lang/invoke/LambdaMetafactory
  #195 = Utf8               metafactory
  #196 = Utf8               (Ljava/lang/invoke/MethodHandles$Lookup;Ljava/lang/String;Ljava/lang/invoke/MethodType;Ljava/lang/invoke/MethodType;Ljava/lang/invoke/MethodHandle;Ljava/lang/invoke/MethodType;)Ljava/lang/invoke/CallSite;
  #197 = Utf8               InnerClasses
  #198 = Utf8               BlockyAnimation
  #199 = Class              #200          // java/lang/invoke/MethodHandles$Lookup
  #200 = Utf8               java/lang/invoke/MethodHandles$Lookup
  #201 = Class              #202          // java/lang/invoke/MethodHandles
  #202 = Utf8               java/lang/invoke/MethodHandles
  #203 = Utf8               Lookup
{
  public static final com.hypixel.hytale.logger.HytaleLogger LOGGER;
    descriptor: Lcom/hypixel/hytale/logger/HytaleLogger;
    flags: (0x0019) ACC_PUBLIC, ACC_STATIC, ACC_FINAL

  private static final java.util.Map<java.lang.String, com.hypixel.hytale.server.core.asset.common.BlockyAnimationCache$BlockyAnimation> animations;
    descriptor: Ljava/util/Map;
    flags: (0x001a) ACC_PRIVATE, ACC_STATIC, ACC_FINAL
    Signature: #141                         // Ljava/util/Map<Ljava/lang/String;Lcom/hypixel/hytale/server/core/asset/common/BlockyAnimationCache$BlockyAnimation;>;

  public com.hypixel.hytale.server.core.asset.common.BlockyAnimationCache();
    descriptor: ()V
    flags: (0x0001) ACC_PUBLIC
    Code:
      stack=1, locals=1, args_size=1
         0: aload_0
         1: invokespecial #1                  // Method java/lang/Object."<init>":()V
         4: return
      LineNumberTable:
        line 26: 0
      LocalVariableTable:
        Start  Length  Slot  Name   Signature
            0       5     0  this   Lcom/hypixel/hytale/server/core/asset/common/BlockyAnimationCache;

  public static java.util.concurrent.CompletableFuture<com.hypixel.hytale.server.core.asset.common.BlockyAnimationCache$BlockyAnimation> get(java.lang.String);
    descriptor: (Ljava/lang/String;)Ljava/util/concurrent/CompletableFuture;
    flags: (0x0009) ACC_PUBLIC, ACC_STATIC
    Code:
      stack=2, locals=3, args_size=1
         0: getstatic     #7                  // Field animations:Ljava/util/Map;
         3: aload_0
         4: invokeinterface #13,  2           // InterfaceMethod java/util/Map.get:(Ljava/lang/Object;)Ljava/lang/Object;
         9: checkcast     #19                 // class com/hypixel/hytale/server/core/asset/common/BlockyAnimationCache$BlockyAnimation
        12: astore_1
        13: aload_1
        14: ifnull        22
        17: aload_1
        18: invokestatic  #21                 // Method java/util/concurrent/CompletableFuture.completedFuture:(Ljava/lang/Object;)Ljava/util/concurrent/CompletableFuture;
        21: areturn
        22: aload_0
        23: invokestatic  #27                 // Method com/hypixel/hytale/server/core/asset/common/CommonAssetRegistry.getByName:(Ljava/lang/String;)Lcom/hypixel/hytale/server/core/asset/common/CommonAsset;
        26: astore_2
        27: aload_2
        28: ifnonnull     36
        31: aconst_null
        32: invokestatic  #21                 // Method java/util/concurrent/CompletableFuture.completedFuture:(Ljava/lang/Object;)Ljava/util/concurrent/CompletableFuture;
        35: areturn
        36: aload_2
        37: invokestatic  #33                 // Method get0:(Lcom/hypixel/hytale/server/core/asset/common/CommonAsset;)Ljava/util/concurrent/CompletableFuture;
        40: areturn
      LineNumberTable:
        line 33: 0
        line 34: 13
        line 35: 22
        line 36: 27
        line 37: 36
      LocalVariableTable:
        Start  Length  Slot  Name   Signature
            0      41     0  name   Ljava/lang/String;
           13      28     1 animationData   Lcom/hypixel/hytale/server/core/asset/common/BlockyAnimationCache$BlockyAnimation;
           27      14     2 asset   Lcom/hypixel/hytale/server/core/asset/common/CommonAsset;
      StackMapTable: number_of_entries = 2
        frame_type = 252 /* append */
          offset_delta = 22
          locals = [ class com/hypixel/hytale/server/core/asset/common/BlockyAnimationCache$BlockyAnimation ]
        frame_type = 252 /* append */
          offset_delta = 13
          locals = [ class com/hypixel/hytale/server/core/asset/common/CommonAsset ]
    Signature: #155                         // (Ljava/lang/String;)Ljava/util/concurrent/CompletableFuture<Lcom/hypixel/hytale/server/core/asset/common/BlockyAnimationCache$BlockyAnimation;>;
    RuntimeVisibleAnnotations:
      0: #157()
        javax.annotation.Nonnull

  public static java.util.concurrent.CompletableFuture<com.hypixel.hytale.server.core.asset.common.BlockyAnimationCache$BlockyAnimation> get(com.hypixel.hytale.server.core.asset.common.CommonAsset);
    descriptor: (Lcom/hypixel/hytale/server/core/asset/common/CommonAsset;)Ljava/util/concurrent/CompletableFuture;
    flags: (0x0009) ACC_PUBLIC, ACC_STATIC
    Code:
      stack=2, locals=2, args_size=1
         0: getstatic     #7                  // Field animations:Ljava/util/Map;
         3: aload_0
         4: invokevirtual #37                 // Method com/hypixel/hytale/server/core/asset/common/CommonAsset.getName:()Ljava/lang/String;
         7: invokeinterface #13,  2           // InterfaceMethod java/util/Map.get:(Ljava/lang/Object;)Ljava/lang/Object;
        12: checkcast     #19                 // class com/hypixel/hytale/server/core/asset/common/BlockyAnimationCache$BlockyAnimation
        15: astore_1
        16: aload_1
        17: ifnull        25
        20: aload_1
        21: invokestatic  #21                 // Method java/util/concurrent/CompletableFuture.completedFuture:(Ljava/lang/Object;)Ljava/util/concurrent/CompletableFuture;
        24: areturn
        25: aload_0
        26: invokestatic  #33                 // Method get0:(Lcom/hypixel/hytale/server/core/asset/common/CommonAsset;)Ljava/util/concurrent/CompletableFuture;
        29: areturn
      LineNumberTable:
        line 42: 0
        line 43: 16
        line 44: 25
      LocalVariableTable:
        Start  Length  Slot  Name   Signature
            0      30     0 asset   Lcom/hypixel/hytale/server/core/asset/common/CommonAsset;
           16      14     1 animationData   Lcom/hypixel/hytale/server/core/asset/common/BlockyAnimationCache$BlockyAnimation;
      StackMapTable: number_of_entries = 1
        frame_type = 252 /* append */
          offset_delta = 25
          locals = [ class com/hypixel/hytale/server/core/asset/common/BlockyAnimationCache$BlockyAnimation ]
    Signature: #158                         // (Lcom/hypixel/hytale/server/core/asset/common/CommonAsset;)Ljava/util/concurrent/CompletableFuture<Lcom/hypixel/hytale/server/core/asset/common/BlockyAnimationCache$BlockyAnimation;>;
    RuntimeVisibleAnnotations:
      0: #157()
        javax.annotation.Nonnull
    RuntimeVisibleParameterAnnotations:
      parameter 0:
        0: #157()
          javax.annotation.Nonnull

  public static com.hypixel.hytale.server.core.asset.common.BlockyAnimationCache$BlockyAnimation getNow(java.lang.String);
    descriptor: (Ljava/lang/String;)Lcom/hypixel/hytale/server/core/asset/common/BlockyAnimationCache$BlockyAnimation;
    flags: (0x0009) ACC_PUBLIC, ACC_STATIC
    Code:
      stack=2, locals=3, args_size=1
         0: getstatic     #7                  // Field animations:Ljava/util/Map;
         3: aload_0
         4: invokeinterface #13,  2           // InterfaceMethod java/util/Map.get:(Ljava/lang/Object;)Ljava/lang/Object;
         9: checkcast     #19                 // class com/hypixel/hytale/server/core/asset/common/BlockyAnimationCache$BlockyAnimation
        12: astore_1
        13: aload_1
        14: ifnull        19
        17: aload_1
        18: areturn
        19: aload_0
        20: invokestatic  #27                 // Method com/hypixel/hytale/server/core/asset/common/CommonAssetRegistry.getByName:(Ljava/lang/String;)Lcom/hypixel/hytale/server/core/asset/common/CommonAsset;
        23: astore_2
        24: aload_2
        25: ifnonnull     30
        28: aconst_null
        29: areturn
        30: aload_2
        31: invokestatic  #33                 // Method get0:(Lcom/hypixel/hytale/server/core/asset/common/CommonAsset;)Ljava/util/concurrent/CompletableFuture;
        34: invokevirtual #43                 // Method java/util/concurrent/CompletableFuture.join:()Ljava/lang/Object;
        37: checkcast     #19                 // class com/hypixel/hytale/server/core/asset/common/BlockyAnimationCache$BlockyAnimation
        40: areturn
      LineNumberTable:
        line 49: 0
        line 50: 13
        line 51: 19
        line 52: 24
        line 53: 30
      LocalVariableTable:
        Start  Length  Slot  Name   Signature
            0      41     0  name   Ljava/lang/String;
           13      28     1 animationData   Lcom/hypixel/hytale/server/core/asset/common/BlockyAnimationCache$BlockyAnimation;
           24      17     2 asset   Lcom/hypixel/hytale/server/core/asset/common/CommonAsset;
      StackMapTable: number_of_entries = 2
        frame_type = 252 /* append */
          offset_delta = 19
          locals = [ class com/hypixel/hytale/server/core/asset/common/BlockyAnimationCache$BlockyAnimation ]
        frame_type = 252 /* append */
          offset_delta = 10
          locals = [ class com/hypixel/hytale/server/core/asset/common/CommonAsset ]
    RuntimeVisibleAnnotations:
      0: #162()
        javax.annotation.Nullable

  public static com.hypixel.hytale.server.core.asset.common.BlockyAnimationCache$BlockyAnimation getNow(com.hypixel.hytale.server.core.asset.common.CommonAsset);
    descriptor: (Lcom/hypixel/hytale/server/core/asset/common/CommonAsset;)Lcom/hypixel/hytale/server/core/asset/common/BlockyAnimationCache$BlockyAnimation;
    flags: (0x0009) ACC_PUBLIC, ACC_STATIC
    Code:
      stack=2, locals=2, args_size=1
         0: getstatic     #7                  // Field animations:Ljava/util/Map;
         3: aload_0
         4: invokevirtual #37                 // Method com/hypixel/hytale/server/core/asset/common/CommonAsset.getName:()Ljava/lang/String;
         7: invokeinterface #13,  2           // InterfaceMethod java/util/Map.get:(Ljava/lang/Object;)Ljava/lang/Object;
        12: checkcast     #19                 // class com/hypixel/hytale/server/core/asset/common/BlockyAnimationCache$BlockyAnimation
        15: astore_1
        16: aload_1
        17: ifnull        22
        20: aload_1
        21: areturn
        22: aload_0
        23: invokestatic  #33                 // Method get0:(Lcom/hypixel/hytale/server/core/asset/common/CommonAsset;)Ljava/util/concurrent/CompletableFuture;
        26: invokevirtual #43                 // Method java/util/concurrent/CompletableFuture.join:()Ljava/lang/Object;
        29: checkcast     #19                 // class com/hypixel/hytale/server/core/asset/common/BlockyAnimationCache$BlockyAnimation
        32: areturn
      LineNumberTable:
        line 57: 0
        line 58: 16
        line 59: 22
      LocalVariableTable:
        Start  Length  Slot  Name   Signature
            0      33     0 asset   Lcom/hypixel/hytale/server/core/asset/common/CommonAsset;
           16      17     1 animationData   Lcom/hypixel/hytale/server/core/asset/common/BlockyAnimationCache$BlockyAnimation;
      StackMapTable: number_of_entries = 1
        frame_type = 252 /* append */
          offset_delta = 22
          locals = [ class com/hypixel/hytale/server/core/asset/common/BlockyAnimationCache$BlockyAnimation ]
    RuntimeVisibleParameterAnnotations:
      parameter 0:
        0: #157()
          javax.annotation.Nonnull

  private static java.util.concurrent.CompletableFuture<com.hypixel.hytale.server.core.asset.common.BlockyAnimationCache$BlockyAnimation> get0(com.hypixel.hytale.server.core.asset.common.CommonAsset);
    descriptor: (Lcom/hypixel/hytale/server/core/asset/common/CommonAsset;)Ljava/util/concurrent/CompletableFuture;
    flags: (0x000a) ACC_PRIVATE, ACC_STATIC
    Code:
      stack=2, locals=2, args_size=1
         0: aload_0
         1: invokevirtual #37                 // Method com/hypixel/hytale/server/core/asset/common/CommonAsset.getName:()Ljava/lang/String;
         4: astore_1
         5: aload_0
         6: invokevirtual #47                 // Method com/hypixel/hytale/server/core/asset/common/CommonAsset.getBlob:()Ljava/util/concurrent/CompletableFuture;
         9: aload_1
        10: invokedynamic #51,  0             // InvokeDynamic #0:apply:(Ljava/lang/String;)Ljava/util/function/Function;
        15: invokevirtual #55                 // Method java/util/concurrent/CompletableFuture.thenApply:(Ljava/util/function/Function;)Ljava/util/concurrent/CompletableFuture;
        18: invokestatic  #59                 // Method com/hypixel/hytale/common/util/CompletableFutureUtil._catch:(Ljava/util/concurrent/CompletableFuture;)Ljava/util/concurrent/CompletableFuture;
        21: areturn
      LineNumberTable:
        line 64: 0
        line 65: 5
      LocalVariableTable:
        Start  Length  Slot  Name   Signature
            0      22     0 asset   Lcom/hypixel/hytale/server/core/asset/common/CommonAsset;
            5      17     1  name   Ljava/lang/String;
    Signature: #158                         // (Lcom/hypixel/hytale/server/core/asset/common/CommonAsset;)Ljava/util/concurrent/CompletableFuture<Lcom/hypixel/hytale/server/core/asset/common/BlockyAnimationCache$BlockyAnimation;>;
    RuntimeVisibleAnnotations:
      0: #157()
        javax.annotation.Nonnull
    RuntimeVisibleParameterAnnotations:
      parameter 0:
        0: #157()
          javax.annotation.Nonnull

  public static void invalidate(java.lang.String);
    descriptor: (Ljava/lang/String;)V
    flags: (0x0009) ACC_PUBLIC, ACC_STATIC
    Code:
      stack=2, locals=1, args_size=1
         0: getstatic     #7                  // Field animations:Ljava/util/Map;
         3: aload_0
         4: invokeinterface #65,  2           // InterfaceMethod java/util/Map.remove:(Ljava/lang/Object;)Ljava/lang/Object;
         9: pop
        10: return
      LineNumberTable:
        line 81: 0
        line 82: 10
      LocalVariableTable:
        Start  Length  Slot  Name   Signature
            0      11     0  name   Ljava/lang/String;

  private static com.hypixel.hytale.server.core.asset.common.BlockyAnimationCache$BlockyAnimation lambda$get0$0(java.lang.String, byte[]);
    descriptor: (Ljava/lang/String;[B)Lcom/hypixel/hytale/server/core/asset/common/BlockyAnimationCache$BlockyAnimation;
    flags: (0x100a) ACC_PRIVATE, ACC_STATIC, ACC_SYNTHETIC
    Code:
      stack=4, locals=6, args_size=2
         0: new           #68                 // class java/lang/String
         3: dup
         4: aload_1
         5: getstatic     #70                 // Field java/nio/charset/StandardCharsets.UTF_8:Ljava/nio/charset/Charset;
         8: invokespecial #76                 // Method java/lang/String."<init>":([BLjava/nio/charset/Charset;)V
        11: astore_2
        12: aload_2
        13: invokestatic  #79                 // Method com/hypixel/hytale/codec/util/RawJsonReader.fromJsonString:(Ljava/lang/String;)Lcom/hypixel/hytale/codec/util/RawJsonReader;
        16: astore_3
        17: getstatic     #85                 // Field com/hypixel/hytale/codec/ExtraInfo.THREAD_LOCAL:Ljava/lang/ThreadLocal;
        20: invokevirtual #91                 // Method java/lang/ThreadLocal.get:()Ljava/lang/Object;
        23: checkcast     #86                 // class com/hypixel/hytale/codec/ExtraInfo
        26: astore        4
        28: getstatic     #95                 // Field com/hypixel/hytale/server/core/asset/common/BlockyAnimationCache$BlockyAnimation.CODEC:Lcom/hypixel/hytale/codec/builder/BuilderCodec;
        31: aload_3
        32: aload         4
        34: invokevirtual #99                 // Method com/hypixel/hytale/codec/builder/BuilderCodec.decodeJson:(Lcom/hypixel/hytale/codec/util/RawJsonReader;Lcom/hypixel/hytale/codec/ExtraInfo;)Ljava/lang/Object;
        37: checkcast     #19                 // class com/hypixel/hytale/server/core/asset/common/BlockyAnimationCache$BlockyAnimation
        40: astore        5
        42: aload         4
        44: invokevirtual #105                // Method com/hypixel/hytale/codec/ExtraInfo.getValidationResults:()Lcom/hypixel/hytale/codec/validation/ValidationResults;
        47: getstatic     #109                // Field LOGGER:Lcom/hypixel/hytale/logger/HytaleLogger;
        50: invokevirtual #113                // Method com/hypixel/hytale/codec/validation/ValidationResults.logOrThrowValidatorExceptions:(Lcom/hypixel/hytale/logger/HytaleLogger;)V
        53: getstatic     #7                  // Field animations:Ljava/util/Map;
        56: aload_0
        57: aload         5
        59: invokeinterface #119,  3          // InterfaceMethod java/util/Map.put:(Ljava/lang/Object;Ljava/lang/Object;)Ljava/lang/Object;
        64: pop
        65: aload         5
        67: areturn
        68: astore        4
        70: aload         4
        72: invokestatic  #125                // Method com/hypixel/hytale/sneakythrow/SneakyThrow.sneakyThrow:(Ljava/lang/Throwable;)Ljava/lang/RuntimeException;
        75: athrow
      Exception table:
         from    to  target type
            17    67    68   Class java/io/IOException
      LineNumberTable:
        line 66: 0
        line 67: 12
        line 69: 17
        line 70: 28
        line 71: 42
        line 72: 53
        line 73: 65
        line 74: 68
        line 75: 70
      LocalVariableTable:
        Start  Length  Slot  Name   Signature
           28      40     4 extraInfo   Lcom/hypixel/hytale/codec/ExtraInfo;
           42      26     5 newAnimationData   Lcom/hypixel/hytale/server/core/asset/common/BlockyAnimationCache$BlockyAnimation;
           70       6     4     e   Ljava/io/IOException;
            0      76     0  name   Ljava/lang/String;
            0      76     1 bytes   [B
           12      64     2   str   Ljava/lang/String;
           17      59     3 reader   Lcom/hypixel/hytale/codec/util/RawJsonReader;
      StackMapTable: number_of_entries = 1
        frame_type = 255 /* full_frame */
          offset_delta = 68
          locals = [ class java/lang/String, class "[B", class java/lang/String, class com/hypixel/hytale/codec/util/RawJsonReader ]
          stack = [ class java/io/IOException ]

  static {};
    descriptor: ()V
    flags: (0x0008) ACC_STATIC
    Code:
      stack=2, locals=0, args_size=0
         0: invokestatic  #131                // Method com/hypixel/hytale/logger/HytaleLogger.forEnclosingClass:()Lcom/hypixel/hytale/logger/HytaleLogger;
         3: putstatic     #109                // Field LOGGER:Lcom/hypixel/hytale/logger/HytaleLogger;
         6: new           #137                // class java/util/concurrent/ConcurrentHashMap
         9: dup
        10: invokespecial #139                // Method java/util/concurrent/ConcurrentHashMap."<init>":()V
        13: putstatic     #7                  // Field animations:Ljava/util/Map;
        16: return
      LineNumberTable:
        line 27: 0
        line 29: 6
}
SourceFile: "BlockyAnimationCache.java"
NestMembers:
  com/hypixel/hytale/server/core/asset/common/BlockyAnimationCache$BlockyAnimation
BootstrapMethods:
  0: #190 REF_invokeStatic java/lang/invoke/LambdaMetafactory.metafactory:(Ljava/lang/invoke/MethodHandles$Lookup;Ljava/lang/String;Ljava/lang/invoke/MethodType;Ljava/lang/invoke/MethodType;Ljava/lang/invoke/MethodHandle;Ljava/lang/invoke/MethodType;)Ljava/lang/invoke/CallSite;
    Method arguments:
      #184 (Ljava/lang/Object;)Ljava/lang/Object;
      #185 REF_invokeStatic com/hypixel/hytale/server/core/asset/common/BlockyAnimationCache.lambda$get0$0:(Ljava/lang/String;[B)Lcom/hypixel/hytale/server/core/asset/common/BlockyAnimationCache$BlockyAnimation;
      #188 ([B)Lcom/hypixel/hytale/server/core/asset/common/BlockyAnimationCache$BlockyAnimation;
InnerClasses:
  public static #198= #19 of #8;          // BlockyAnimation=class com/hypixel/hytale/server/core/asset/common/BlockyAnimationCache$BlockyAnimation of class com/hypixel/hytale/server/core/asset/common/BlockyAnimationCache
  public static final #203= #199 of #201; // Lookup=class java/lang/invoke/MethodHandles$Lookup of class java/lang/invoke/MethodHandles
