Classfile jar:file:///C:/Users/henry/.m2/repository/com/hypixel/hytale/hytale-server/2026.01.15/hytale-server-2026.01.15.jar!/com/hypixel/hytale/server/core/event/events/ecs/BreakBlockEvent.class
  Last modified Jan 17, 2026; size 1683 bytes
  SHA-256 checksum 63df172a219b11420be35eb1d7ef0e924c802b90fdbe335890f1c44fba6ecc14
  Compiled from "BreakBlockEvent.java"
public class com.hypixel.hytale.server.core.event.events.ecs.BreakBlockEvent extends com.hypixel.hytale.component.system.CancellableEcsEvent
  minor version: 0
  major version: 65
  flags: (0x0021) ACC_PUBLIC, ACC_SUPER
  this_class: #8                          // com/hypixel/hytale/server/core/event/events/ecs/BreakBlockEvent
  super_class: #2                         // com/hypixel/hytale/component/system/CancellableEcsEvent
  interfaces: 0, fields: 3, methods: 5, attributes: 1
Constant pool:
   #1 = Methodref          #2.#3          // com/hypixel/hytale/component/system/CancellableEcsEvent."<init>":()V
   #2 = Class              #4             // com/hypixel/hytale/component/system/CancellableEcsEvent
   #3 = NameAndType        #5:#6          // "<init>":()V
   #4 = Utf8               com/hypixel/hytale/component/system/CancellableEcsEvent
   #5 = Utf8               <init>
   #6 = Utf8               ()V
   #7 = Fieldref           #8.#9          // com/hypixel/hytale/server/core/event/events/ecs/BreakBlockEvent.itemInHand:Lcom/hypixel/hytale/server/core/inventory/ItemStack;
   #8 = Class              #10            // com/hypixel/hytale/server/core/event/events/ecs/BreakBlockEvent
   #9 = NameAndType        #11:#12        // itemInHand:Lcom/hypixel/hytale/server/core/inventory/ItemStack;
  #10 = Utf8               com/hypixel/hytale/server/core/event/events/ecs/BreakBlockEvent
  #11 = Utf8               itemInHand
  #12 = Utf8               Lcom/hypixel/hytale/server/core/inventory/ItemStack;
  #13 = Fieldref           #8.#14         // com/hypixel/hytale/server/core/event/events/ecs/BreakBlockEvent.targetBlock:Lcom/hypixel/hytale/math/vector/Vector3i;
  #14 = NameAndType        #15:#16        // targetBlock:Lcom/hypixel/hytale/math/vector/Vector3i;
  #15 = Utf8               targetBlock
  #16 = Utf8               Lcom/hypixel/hytale/math/vector/Vector3i;
  #17 = Fieldref           #8.#18         // com/hypixel/hytale/server/core/event/events/ecs/BreakBlockEvent.blockType:Lcom/hypixel/hytale/server/core/asset/type/blocktype/config/BlockType;
  #18 = NameAndType        #19:#20        // blockType:Lcom/hypixel/hytale/server/core/asset/type/blocktype/config/BlockType;
  #19 = Utf8               blockType
  #20 = Utf8               Lcom/hypixel/hytale/server/core/asset/type/blocktype/config/BlockType;
  #21 = Utf8               RuntimeVisibleAnnotations
  #22 = Utf8               Ljavax/annotation/Nullable;
  #23 = Utf8               Ljavax/annotation/Nonnull;
  #24 = Utf8               (Lcom/hypixel/hytale/server/core/inventory/ItemStack;Lcom/hypixel/hytale/math/vector/Vector3i;Lcom/hypixel/hytale/server/core/asset/type/blocktype/config/BlockType;)V
  #25 = Utf8               Code
  #26 = Utf8               LineNumberTable
  #27 = Utf8               LocalVariableTable
  #28 = Utf8               this
  #29 = Utf8               Lcom/hypixel/hytale/server/core/event/events/ecs/BreakBlockEvent;
  #30 = Utf8               RuntimeVisibleParameterAnnotations
  #31 = Utf8               getItemInHand
  #32 = Utf8               ()Lcom/hypixel/hytale/server/core/inventory/ItemStack;
  #33 = Utf8               getTargetBlock
  #34 = Utf8               ()Lcom/hypixel/hytale/math/vector/Vector3i;
  #35 = Utf8               getBlockType
  #36 = Utf8               ()Lcom/hypixel/hytale/server/core/asset/type/blocktype/config/BlockType;
  #37 = Utf8               setTargetBlock
  #38 = Utf8               (Lcom/hypixel/hytale/math/vector/Vector3i;)V
  #39 = Utf8               SourceFile
  #40 = Utf8               BreakBlockEvent.java
{
  private final com.hypixel.hytale.server.core.inventory.ItemStack itemInHand;
    descriptor: Lcom/hypixel/hytale/server/core/inventory/ItemStack;
    flags: (0x0012) ACC_PRIVATE, ACC_FINAL
    RuntimeVisibleAnnotations:
      0: #22()
        javax.annotation.Nullable

  private com.hypixel.hytale.math.vector.Vector3i targetBlock;
    descriptor: Lcom/hypixel/hytale/math/vector/Vector3i;
    flags: (0x0002) ACC_PRIVATE
    RuntimeVisibleAnnotations:
      0: #23()
        javax.annotation.Nonnull

  private final com.hypixel.hytale.server.core.asset.type.blocktype.config.BlockType blockType;
    descriptor: Lcom/hypixel/hytale/server/core/asset/type/blocktype/config/BlockType;
    flags: (0x0012) ACC_PRIVATE, ACC_FINAL
    RuntimeVisibleAnnotations:
      0: #23()
        javax.annotation.Nonnull

  public com.hypixel.hytale.server.core.event.events.ecs.BreakBlockEvent(com.hypixel.hytale.server.core.inventory.ItemStack, com.hypixel.hytale.math.vector.Vector3i, com.hypixel.hytale.server.core.asset.type.blocktype.config.BlockType);
    descriptor: (Lcom/hypixel/hytale/server/core/inventory/ItemStack;Lcom/hypixel/hytale/math/vector/Vector3i;Lcom/hypixel/hytale/server/core/asset/type/blocktype/config/BlockType;)V
    flags: (0x0001) ACC_PUBLIC
    Code:
      stack=2, locals=4, args_size=4
         0: aload_0
         1: invokespecial #1                  // Method com/hypixel/hytale/component/system/CancellableEcsEvent."<init>":()V
         4: aload_0
         5: aload_1
         6: putfield      #7                  // Field itemInHand:Lcom/hypixel/hytale/server/core/inventory/ItemStack;
         9: aload_0
        10: aload_2
        11: putfield      #13                 // Field targetBlock:Lcom/hypixel/hytale/math/vector/Vector3i;
        14: aload_0
        15: aload_3
        16: putfield      #17                 // Field blockType:Lcom/hypixel/hytale/server/core/asset/type/blocktype/config/BlockType;
        19: return
      LineNumberTable:
        line 43: 0
        line 44: 4
        line 45: 9
        line 46: 14
        line 47: 19
      LocalVariableTable:
        Start  Length  Slot  Name   Signature
            0      20     0  this   Lcom/hypixel/hytale/server/core/event/events/ecs/BreakBlockEvent;
            0      20     1 itemInHand   Lcom/hypixel/hytale/server/core/inventory/ItemStack;
            0      20     2 targetBlock   Lcom/hypixel/hytale/math/vector/Vector3i;
            0      20     3 blockType   Lcom/hypixel/hytale/server/core/asset/type/blocktype/config/BlockType;
    RuntimeVisibleParameterAnnotations:
      parameter 0:
        0: #22()
          javax.annotation.Nullable
      parameter 1:
        0: #23()
          javax.annotation.Nonnull
      parameter 2:
        0: #23()
          javax.annotation.Nonnull

  public com.hypixel.hytale.server.core.inventory.ItemStack getItemInHand();
    descriptor: ()Lcom/hypixel/hytale/server/core/inventory/ItemStack;
    flags: (0x0001) ACC_PUBLIC
    Code:
      stack=1, locals=1, args_size=1
         0: aload_0
         1: getfield      #7                  // Field itemInHand:Lcom/hypixel/hytale/server/core/inventory/ItemStack;
         4: areturn
      LineNumberTable:
        line 54: 0
      LocalVariableTable:
        Start  Length  Slot  Name   Signature
            0       5     0  this   Lcom/hypixel/hytale/server/core/event/events/ecs/BreakBlockEvent;
    RuntimeVisibleAnnotations:
      0: #22()
        javax.annotation.Nullable

  public com.hypixel.hytale.math.vector.Vector3i getTargetBlock();
    descriptor: ()Lcom/hypixel/hytale/math/vector/Vector3i;
    flags: (0x0001) ACC_PUBLIC
    Code:
      stack=1, locals=1, args_size=1
         0: aload_0
         1: getfield      #13                 // Field targetBlock:Lcom/hypixel/hytale/math/vector/Vector3i;
         4: areturn
      LineNumberTable:
        line 62: 0
      LocalVariableTable:
        Start  Length  Slot  Name   Signature
            0       5     0  this   Lcom/hypixel/hytale/server/core/event/events/ecs/BreakBlockEvent;
    RuntimeVisibleAnnotations:
      0: #23()
        javax.annotation.Nonnull

  public com.hypixel.hytale.server.core.asset.type.blocktype.config.BlockType getBlockType();
    descriptor: ()Lcom/hypixel/hytale/server/core/asset/type/blocktype/config/BlockType;
    flags: (0x0001) ACC_PUBLIC
    Code:
      stack=1, locals=1, args_size=1
         0: aload_0
         1: getfield      #17                 // Field blockType:Lcom/hypixel/hytale/server/core/asset/type/blocktype/config/BlockType;
         4: areturn
      LineNumberTable:
        line 70: 0
      LocalVariableTable:
        Start  Length  Slot  Name   Signature
            0       5     0  this   Lcom/hypixel/hytale/server/core/event/events/ecs/BreakBlockEvent;
    RuntimeVisibleAnnotations:
      0: #23()
        javax.annotation.Nonnull

  public void setTargetBlock(com.hypixel.hytale.math.vector.Vector3i);
    descriptor: (Lcom/hypixel/hytale/math/vector/Vector3i;)V
    flags: (0x0001) ACC_PUBLIC
    Code:
      stack=2, locals=2, args_size=2
         0: aload_0
         1: aload_1
         2: putfield      #13                 // Field targetBlock:Lcom/hypixel/hytale/math/vector/Vector3i;
         5: return
      LineNumberTable:
        line 77: 0
        line 78: 5
      LocalVariableTable:
        Start  Length  Slot  Name   Signature
            0       6     0  this   Lcom/hypixel/hytale/server/core/event/events/ecs/BreakBlockEvent;
            0       6     1 targetBlock   Lcom/hypixel/hytale/math/vector/Vector3i;
    RuntimeVisibleParameterAnnotations:
      parameter 0:
        0: #23()
          javax.annotation.Nonnull
}
SourceFile: "BreakBlockEvent.java"
