Classfile jar:file:///C:/Users/henry/.m2/repository/com/hypixel/hytale/hytale-server/2026.01.15/hytale-server-2026.01.15.jar!/com/hypixel/hytale/server/core/plugin/JavaPlugin.class
  Last modified Jan 17, 2026; size 3217 bytes
  SHA-256 checksum ada50de68aedf854918ae6488e537ed3ea78220e701b6e167efe316c30b5252a
  Compiled from "JavaPlugin.java"
public abstract class com.hypixel.hytale.server.core.plugin.JavaPlugin extends com.hypixel.hytale.server.core.plugin.PluginBase
  minor version: 0
  major version: 65
  flags: (0x0421) ACC_PUBLIC, ACC_SUPER, ACC_ABSTRACT
  this_class: #14                         // com/hypixel/hytale/server/core/plugin/JavaPlugin
  super_class: #2                         // com/hypixel/hytale/server/core/plugin/PluginBase
  interfaces: 0, fields: 2, methods: 5, attributes: 2
Constant pool:
    #1 = Methodref          #2.#3         // com/hypixel/hytale/server/core/plugin/PluginBase."<init>":(Lcom/hypixel/hytale/server/core/plugin/PluginInit;)V
    #2 = Class              #4            // com/hypixel/hytale/server/core/plugin/PluginBase
    #3 = NameAndType        #5:#6         // "<init>":(Lcom/hypixel/hytale/server/core/plugin/PluginInit;)V
    #4 = Utf8               com/hypixel/hytale/server/core/plugin/PluginBase
    #5 = Utf8               <init>
    #6 = Utf8               (Lcom/hypixel/hytale/server/core/plugin/PluginInit;)V
    #7 = Methodref          #8.#9         // com/hypixel/hytale/server/core/plugin/JavaPluginInit.getFile:()Ljava/nio/file/Path;
    #8 = Class              #10           // com/hypixel/hytale/server/core/plugin/JavaPluginInit
    #9 = NameAndType        #11:#12       // getFile:()Ljava/nio/file/Path;
   #10 = Utf8               com/hypixel/hytale/server/core/plugin/JavaPluginInit
   #11 = Utf8               getFile
   #12 = Utf8               ()Ljava/nio/file/Path;
   #13 = Fieldref           #14.#15       // com/hypixel/hytale/server/core/plugin/JavaPlugin.file:Ljava/nio/file/Path;
   #14 = Class              #16           // com/hypixel/hytale/server/core/plugin/JavaPlugin
   #15 = NameAndType        #17:#18       // file:Ljava/nio/file/Path;
   #16 = Utf8               com/hypixel/hytale/server/core/plugin/JavaPlugin
   #17 = Utf8               file
   #18 = Utf8               Ljava/nio/file/Path;
   #19 = Methodref          #8.#20        // com/hypixel/hytale/server/core/plugin/JavaPluginInit.getClassLoader:()Lcom/hypixel/hytale/server/core/plugin/PluginClassLoader;
   #20 = NameAndType        #21:#22       // getClassLoader:()Lcom/hypixel/hytale/server/core/plugin/PluginClassLoader;
   #21 = Utf8               getClassLoader
   #22 = Utf8               ()Lcom/hypixel/hytale/server/core/plugin/PluginClassLoader;
   #23 = Fieldref           #14.#24       // com/hypixel/hytale/server/core/plugin/JavaPlugin.classLoader:Lcom/hypixel/hytale/server/core/plugin/PluginClassLoader;
   #24 = NameAndType        #25:#26       // classLoader:Lcom/hypixel/hytale/server/core/plugin/PluginClassLoader;
   #25 = Utf8               classLoader
   #26 = Utf8               Lcom/hypixel/hytale/server/core/plugin/PluginClassLoader;
   #27 = Methodref          #28.#29       // com/hypixel/hytale/server/core/plugin/PluginClassLoader.setPlugin:(Lcom/hypixel/hytale/server/core/plugin/JavaPlugin;)V
   #28 = Class              #30           // com/hypixel/hytale/server/core/plugin/PluginClassLoader
   #29 = NameAndType        #31:#32       // setPlugin:(Lcom/hypixel/hytale/server/core/plugin/JavaPlugin;)V
   #30 = Utf8               com/hypixel/hytale/server/core/plugin/PluginClassLoader
   #31 = Utf8               setPlugin
   #32 = Utf8               (Lcom/hypixel/hytale/server/core/plugin/JavaPlugin;)V
   #33 = Methodref          #2.#34        // com/hypixel/hytale/server/core/plugin/PluginBase.start0:()V
   #34 = NameAndType        #35:#36       // start0:()V
   #35 = Utf8               start0
   #36 = Utf8               ()V
   #37 = Methodref          #14.#38       // com/hypixel/hytale/server/core/plugin/JavaPlugin.getManifest:()Lcom/hypixel/hytale/common/plugin/PluginManifest;
   #38 = NameAndType        #39:#40       // getManifest:()Lcom/hypixel/hytale/common/plugin/PluginManifest;
   #39 = Utf8               getManifest
   #40 = Utf8               ()Lcom/hypixel/hytale/common/plugin/PluginManifest;
   #41 = Methodref          #42.#43       // com/hypixel/hytale/common/plugin/PluginManifest.includesAssetPack:()Z
   #42 = Class              #44           // com/hypixel/hytale/common/plugin/PluginManifest
   #43 = NameAndType        #45:#46       // includesAssetPack:()Z
   #44 = Utf8               com/hypixel/hytale/common/plugin/PluginManifest
   #45 = Utf8               includesAssetPack
   #46 = Utf8               ()Z
   #47 = Methodref          #48.#49       // com/hypixel/hytale/server/core/asset/AssetModule.get:()Lcom/hypixel/hytale/server/core/asset/AssetModule;
   #48 = Class              #50           // com/hypixel/hytale/server/core/asset/AssetModule
   #49 = NameAndType        #51:#52       // get:()Lcom/hypixel/hytale/server/core/asset/AssetModule;
   #50 = Utf8               com/hypixel/hytale/server/core/asset/AssetModule
   #51 = Utf8               get
   #52 = Utf8               ()Lcom/hypixel/hytale/server/core/asset/AssetModule;
   #53 = Class              #54           // com/hypixel/hytale/common/plugin/PluginIdentifier
   #54 = Utf8               com/hypixel/hytale/common/plugin/PluginIdentifier
   #55 = Methodref          #53.#56       // com/hypixel/hytale/common/plugin/PluginIdentifier."<init>":(Lcom/hypixel/hytale/common/plugin/PluginManifest;)V
   #56 = NameAndType        #5:#57        // "<init>":(Lcom/hypixel/hytale/common/plugin/PluginManifest;)V
   #57 = Utf8               (Lcom/hypixel/hytale/common/plugin/PluginManifest;)V
   #58 = Methodref          #53.#59       // com/hypixel/hytale/common/plugin/PluginIdentifier.toString:()Ljava/lang/String;
   #59 = NameAndType        #60:#61       // toString:()Ljava/lang/String;
   #60 = Utf8               toString
   #61 = Utf8               ()Ljava/lang/String;
   #62 = Methodref          #48.#63       // com/hypixel/hytale/server/core/asset/AssetModule.getAssetPack:(Ljava/lang/String;)Lcom/hypixel/hytale/assetstore/AssetPack;
   #63 = NameAndType        #64:#65       // getAssetPack:(Ljava/lang/String;)Lcom/hypixel/hytale/assetstore/AssetPack;
   #64 = Utf8               getAssetPack
   #65 = Utf8               (Ljava/lang/String;)Lcom/hypixel/hytale/assetstore/AssetPack;
   #66 = Methodref          #14.#67       // com/hypixel/hytale/server/core/plugin/JavaPlugin.getLogger:()Lcom/hypixel/hytale/logger/HytaleLogger;
   #67 = NameAndType        #68:#69       // getLogger:()Lcom/hypixel/hytale/logger/HytaleLogger;
   #68 = Utf8               getLogger
   #69 = Utf8               ()Lcom/hypixel/hytale/logger/HytaleLogger;
   #70 = Fieldref           #71.#72       // java/util/logging/Level.WARNING:Ljava/util/logging/Level;
   #71 = Class              #73           // java/util/logging/Level
   #72 = NameAndType        #74:#75       // WARNING:Ljava/util/logging/Level;
   #73 = Utf8               java/util/logging/Level
   #74 = Utf8               WARNING
   #75 = Utf8               Ljava/util/logging/Level;
   #76 = Methodref          #77.#78       // com/hypixel/hytale/logger/HytaleLogger.at:(Ljava/util/logging/Level;)Lcom/hypixel/hytale/logger/HytaleLogger$Api;
   #77 = Class              #79           // com/hypixel/hytale/logger/HytaleLogger
   #78 = NameAndType        #80:#81       // at:(Ljava/util/logging/Level;)Lcom/hypixel/hytale/logger/HytaleLogger$Api;
   #79 = Utf8               com/hypixel/hytale/logger/HytaleLogger
   #80 = Utf8               at
   #81 = Utf8               (Ljava/util/logging/Level;)Lcom/hypixel/hytale/logger/HytaleLogger$Api;
   #82 = String             #83           // Asset pack %s already exists, skipping embedded pack
   #83 = Utf8               Asset pack %s already exists, skipping embedded pack
   #84 = InterfaceMethodref #85.#86       // com/hypixel/hytale/logger/HytaleLogger$Api.log:(Ljava/lang/String;Ljava/lang/Object;)V
   #85 = Class              #87           // com/hypixel/hytale/logger/HytaleLogger$Api
   #86 = NameAndType        #88:#89       // log:(Ljava/lang/String;Ljava/lang/Object;)V
   #87 = Utf8               com/hypixel/hytale/logger/HytaleLogger$Api
   #88 = Utf8               log
   #89 = Utf8               (Ljava/lang/String;Ljava/lang/Object;)V
   #90 = Methodref          #48.#91       // com/hypixel/hytale/server/core/asset/AssetModule.registerPack:(Ljava/lang/String;Ljava/nio/file/Path;Lcom/hypixel/hytale/common/plugin/PluginManifest;)V
   #91 = NameAndType        #92:#93       // registerPack:(Ljava/lang/String;Ljava/nio/file/Path;Lcom/hypixel/hytale/common/plugin/PluginManifest;)V
   #92 = Utf8               registerPack
   #93 = Utf8               (Ljava/lang/String;Ljava/nio/file/Path;Lcom/hypixel/hytale/common/plugin/PluginManifest;)V
   #94 = Fieldref           #95.#96       // com/hypixel/hytale/server/core/plugin/PluginType.PLUGIN:Lcom/hypixel/hytale/server/core/plugin/PluginType;
   #95 = Class              #97           // com/hypixel/hytale/server/core/plugin/PluginType
   #96 = NameAndType        #98:#99       // PLUGIN:Lcom/hypixel/hytale/server/core/plugin/PluginType;
   #97 = Utf8               com/hypixel/hytale/server/core/plugin/PluginType
   #98 = Utf8               PLUGIN
   #99 = Utf8               Lcom/hypixel/hytale/server/core/plugin/PluginType;
  #100 = Utf8               RuntimeVisibleAnnotations
  #101 = Utf8               Ljavax/annotation/Nonnull;
  #102 = Utf8               (Lcom/hypixel/hytale/server/core/plugin/JavaPluginInit;)V
  #103 = Utf8               Code
  #104 = Utf8               LineNumberTable
  #105 = Utf8               LocalVariableTable
  #106 = Utf8               this
  #107 = Utf8               Lcom/hypixel/hytale/server/core/plugin/JavaPlugin;
  #108 = Utf8               init
  #109 = Utf8               Lcom/hypixel/hytale/server/core/plugin/JavaPluginInit;
  #110 = Utf8               RuntimeVisibleParameterAnnotations
  #111 = Utf8               assetModule
  #112 = Utf8               Lcom/hypixel/hytale/server/core/asset/AssetModule;
  #113 = Utf8               id
  #114 = Utf8               Ljava/lang/String;
  #115 = Utf8               existing
  #116 = Utf8               Lcom/hypixel/hytale/assetstore/AssetPack;
  #117 = Utf8               StackMapTable
  #118 = Class              #119          // java/lang/String
  #119 = Utf8               java/lang/String
  #120 = Class              #121          // com/hypixel/hytale/assetstore/AssetPack
  #121 = Utf8               com/hypixel/hytale/assetstore/AssetPack
  #122 = Utf8               getType
  #123 = Utf8               ()Lcom/hypixel/hytale/server/core/plugin/PluginType;
  #124 = Utf8               SourceFile
  #125 = Utf8               JavaPlugin.java
  #126 = Utf8               InnerClasses
  #127 = Utf8               Api
{
  private final java.nio.file.Path file;
    descriptor: Ljava/nio/file/Path;
    flags: (0x0012) ACC_PRIVATE, ACC_FINAL
    RuntimeVisibleAnnotations:
      0: #101()
        javax.annotation.Nonnull

  private final com.hypixel.hytale.server.core.plugin.PluginClassLoader classLoader;
    descriptor: Lcom/hypixel/hytale/server/core/plugin/PluginClassLoader;
    flags: (0x0012) ACC_PRIVATE, ACC_FINAL
    RuntimeVisibleAnnotations:
      0: #101()
        javax.annotation.Nonnull

  public com.hypixel.hytale.server.core.plugin.JavaPlugin(com.hypixel.hytale.server.core.plugin.JavaPluginInit);
    descriptor: (Lcom/hypixel/hytale/server/core/plugin/JavaPluginInit;)V
    flags: (0x0001) ACC_PUBLIC
    Code:
      stack=2, locals=2, args_size=2
         0: aload_0
         1: aload_1
         2: invokespecial #1                  // Method com/hypixel/hytale/server/core/plugin/PluginBase."<init>":(Lcom/hypixel/hytale/server/core/plugin/PluginInit;)V
         5: aload_0
         6: aload_1
         7: invokevirtual #7                  // Method com/hypixel/hytale/server/core/plugin/JavaPluginInit.getFile:()Ljava/nio/file/Path;
        10: putfield      #13                 // Field file:Ljava/nio/file/Path;
        13: aload_0
        14: aload_1
        15: invokevirtual #19                 // Method com/hypixel/hytale/server/core/plugin/JavaPluginInit.getClassLoader:()Lcom/hypixel/hytale/server/core/plugin/PluginClassLoader;
        18: putfield      #23                 // Field classLoader:Lcom/hypixel/hytale/server/core/plugin/PluginClassLoader;
        21: aload_0
        22: getfield      #23                 // Field classLoader:Lcom/hypixel/hytale/server/core/plugin/PluginClassLoader;
        25: aload_0
        26: invokevirtual #27                 // Method com/hypixel/hytale/server/core/plugin/PluginClassLoader.setPlugin:(Lcom/hypixel/hytale/server/core/plugin/JavaPlugin;)V
        29: return
      LineNumberTable:
        line 33: 0
        line 34: 5
        line 35: 13
        line 36: 21
        line 37: 29
      LocalVariableTable:
        Start  Length  Slot  Name   Signature
            0      30     0  this   Lcom/hypixel/hytale/server/core/plugin/JavaPlugin;
            0      30     1  init   Lcom/hypixel/hytale/server/core/plugin/JavaPluginInit;
    RuntimeVisibleParameterAnnotations:
      parameter 0:
        0: #101()
          javax.annotation.Nonnull

  public java.nio.file.Path getFile();
    descriptor: ()Ljava/nio/file/Path;
    flags: (0x0001) ACC_PUBLIC
    Code:
      stack=1, locals=1, args_size=1
         0: aload_0
         1: getfield      #13                 // Field file:Ljava/nio/file/Path;
         4: areturn
      LineNumberTable:
        line 44: 0
      LocalVariableTable:
        Start  Length  Slot  Name   Signature
            0       5     0  this   Lcom/hypixel/hytale/server/core/plugin/JavaPlugin;
    RuntimeVisibleAnnotations:
      0: #101()
        javax.annotation.Nonnull

  protected void start0();
    descriptor: ()V
    flags: (0x0004) ACC_PROTECTED
    Code:
      stack=4, locals=4, args_size=1
         0: aload_0
         1: invokespecial #33                 // Method com/hypixel/hytale/server/core/plugin/PluginBase.start0:()V
         4: aload_0
         5: invokevirtual #37                 // Method getManifest:()Lcom/hypixel/hytale/common/plugin/PluginManifest;
         8: invokevirtual #41                 // Method com/hypixel/hytale/common/plugin/PluginManifest.includesAssetPack:()Z
        11: ifeq          75
        14: invokestatic  #47                 // Method com/hypixel/hytale/server/core/asset/AssetModule.get:()Lcom/hypixel/hytale/server/core/asset/AssetModule;
        17: astore_1
        18: new           #53                 // class com/hypixel/hytale/common/plugin/PluginIdentifier
        21: dup
        22: aload_0
        23: invokevirtual #37                 // Method getManifest:()Lcom/hypixel/hytale/common/plugin/PluginManifest;
        26: invokespecial #55                 // Method com/hypixel/hytale/common/plugin/PluginIdentifier."<init>":(Lcom/hypixel/hytale/common/plugin/PluginManifest;)V
        29: invokevirtual #58                 // Method com/hypixel/hytale/common/plugin/PluginIdentifier.toString:()Ljava/lang/String;
        32: astore_2
        33: aload_1
        34: aload_2
        35: invokevirtual #62                 // Method com/hypixel/hytale/server/core/asset/AssetModule.getAssetPack:(Ljava/lang/String;)Lcom/hypixel/hytale/assetstore/AssetPack;
        38: astore_3
        39: aload_3
        40: ifnull        62
        43: aload_0
        44: invokevirtual #66                 // Method getLogger:()Lcom/hypixel/hytale/logger/HytaleLogger;
        47: getstatic     #70                 // Field java/util/logging/Level.WARNING:Ljava/util/logging/Level;
        50: invokevirtual #76                 // Method com/hypixel/hytale/logger/HytaleLogger.at:(Ljava/util/logging/Level;)Lcom/hypixel/hytale/logger/HytaleLogger$Api;
        53: ldc           #82                 // String Asset pack %s already exists, skipping embedded pack
        55: aload_2
        56: invokeinterface #84,  3           // InterfaceMethod com/hypixel/hytale/logger/HytaleLogger$Api.log:(Ljava/lang/String;Ljava/lang/Object;)V
        61: return
        62: aload_1
        63: aload_2
        64: aload_0
        65: getfield      #13                 // Field file:Ljava/nio/file/Path;
        68: aload_0
        69: invokevirtual #37                 // Method getManifest:()Lcom/hypixel/hytale/common/plugin/PluginManifest;
        72: invokevirtual #90                 // Method com/hypixel/hytale/server/core/asset/AssetModule.registerPack:(Ljava/lang/String;Ljava/nio/file/Path;Lcom/hypixel/hytale/common/plugin/PluginManifest;)V
        75: return
      LineNumberTable:
        line 49: 0
        line 51: 4
        line 52: 14
        line 53: 18
        line 54: 33
        line 55: 39
        line 58: 43
        line 59: 61
        line 61: 62
        line 63: 75
      LocalVariableTable:
        Start  Length  Slot  Name   Signature
           18      57     1 assetModule   Lcom/hypixel/hytale/server/core/asset/AssetModule;
           33      42     2    id   Ljava/lang/String;
           39      36     3 existing   Lcom/hypixel/hytale/assetstore/AssetPack;
            0      76     0  this   Lcom/hypixel/hytale/server/core/plugin/JavaPlugin;
      StackMapTable: number_of_entries = 2
        frame_type = 254 /* append */
          offset_delta = 62
          locals = [ class com/hypixel/hytale/server/core/asset/AssetModule, class java/lang/String, class com/hypixel/hytale/assetstore/AssetPack ]
        frame_type = 248 /* chop */
          offset_delta = 12

  public com.hypixel.hytale.server.core.plugin.PluginClassLoader getClassLoader();
    descriptor: ()Lcom/hypixel/hytale/server/core/plugin/PluginClassLoader;
    flags: (0x0001) ACC_PUBLIC
    Code:
      stack=1, locals=1, args_size=1
         0: aload_0
         1: getfield      #23                 // Field classLoader:Lcom/hypixel/hytale/server/core/plugin/PluginClassLoader;
         4: areturn
      LineNumberTable:
        line 70: 0
      LocalVariableTable:
        Start  Length  Slot  Name   Signature
            0       5     0  this   Lcom/hypixel/hytale/server/core/plugin/JavaPlugin;
    RuntimeVisibleAnnotations:
      0: #101()
        javax.annotation.Nonnull

  public final com.hypixel.hytale.server.core.plugin.PluginType getType();
    descriptor: ()Lcom/hypixel/hytale/server/core/plugin/PluginType;
    flags: (0x0011) ACC_PUBLIC, ACC_FINAL
    Code:
      stack=1, locals=1, args_size=1
         0: getstatic     #94                 // Field com/hypixel/hytale/server/core/plugin/PluginType.PLUGIN:Lcom/hypixel/hytale/server/core/plugin/PluginType;
         3: areturn
      LineNumberTable:
        line 76: 0
      LocalVariableTable:
        Start  Length  Slot  Name   Signature
            0       4     0  this   Lcom/hypixel/hytale/server/core/plugin/JavaPlugin;
    RuntimeVisibleAnnotations:
      0: #101()
        javax.annotation.Nonnull
}
SourceFile: "JavaPlugin.java"
InnerClasses:
  public static #127= #85 of #77;         // Api=class com/hypixel/hytale/logger/HytaleLogger$Api of class com/hypixel/hytale/logger/HytaleLogger
